{"type":"FeatureCollection", "features":[

   { "type": "Feature",
      "geometry": {
         "type": "LineString",
         "coordinates": [
            [10  ,10],
            [85, 12]
         ]
      },
      "properties": {
         "prop0": "LINE",
         "prop1": 0.0
      }
   },

   { "type": "Feature",
      "geometry": {
         "type": "Polygon",
         "coordinates": [
            [
               [0.0, 30.0],
               [30.0, 30.0],
               [30.0, 0.0],
               [0.0, 20.0],
               [0.0, 30.0]
            ],
            [
               [10.0, 20.0],
               [20.0, 20.0],
               [20.0, 10.0],
               [10.0, 20.0]
            ]
         ]
      },
      "properties": {
         "prop0": "POLYGON",
         "prop1": 0.0
      }
   },

   { "type": "Feature",
      "geometry": {
         "type": "MultiLineString",
         "coordinates": [
            [ [-4.0, 20], [-5.0, 20] ],
            [ [-5.0, 20], [-10, 25] ]
         ]
      },
      "properties": {
         "prop0": "MULTISTRING",
         "prop1": 0.0
      }
   },

   { "type": "Feature",
      "geometry":{
         "type": "MultiPoint",
         "coordinates": [ [-3.0, 16.0 ], [16.0, -4.0] ]
      },
      "properties": {
         "prop0": "POINTS",
         "prop1": 0.0
      }
   },

   {
      "type":"Feature",
      "geometry":{
         "type":"MultiPolygon",
         "coordinates":[
            [
               [
                  [-95.08, 49.36],
                  [-82.13, 43.59],
                  [-83.17, 42.05],
                  [-82.7, 41.68],
                  [-78.99, 42.82],
                  [-79.18, 43.47],
                  [-78.72, 43.63],
                  [-76.8, 43.63],
                  [-74.99, 44.99],
                  [-67.79, 47.07],
                  [-67.8, 45.7],
                  [-67.21, 45.18],
                  [-67.19, 44.66],
                  [-68.8, 44.58],
                  [-70.73, 43.12],
                  [-71.51, 41.37],
                  [-74, 40.71],
                  [-73.96, 41.31],
                  [-76.31, 38.05],
                  [-76.27, 37.08],
                  [-77.23, 37.3],
                  [-75.99, 36.91],
                  [-75.53, 35.8],
                  [-75.94, 36.72],
                  [-80.84, 32.52],
                  [-81.5, 31.13],
                  [-80.03, 26.79],
                  [-80.4, 25.18],
                  [-81.09, 25.12],
                  [-81.74, 25.96],
                  [-85.35, 29.68],
                  [-86.26, 30.5],
                  [-88.02, 30.22],
                  [-90.42, 30.2],
                  [-89.4, 30.05],
                  [-89.75, 29.63],
                  [-89.01, 29.18],
                  [-89.4, 28.93],
                  [-90.18, 29.57],
                  [-96.64, 28.72],
                  [-96.4, 28.44],
                  [-97.52, 27.87],
                  [-99.1, 26.43],
                  [-99.51, 27.57],
                  [-101.41, 29.77],
                  [-103.38, 29.02],
                  [-106.4, 31.75],
                  [-111.05, 31.33],
                  [-113.05, 31.97],
                  [-114.72, 32.72],
                  [-123, 38.01],
                  [-124.33, 40.27],
                  [-124.04, 41.43],
                  [-124.52, 42.87],
                  [-123.16, 46.2],
                  [-124, 46.32],
                  [-123.8, 46.98],
                  [-124.16, 46.94],
                  [-122.76, 49],
                  [-95.08, 49.36]
               ]
            ],
            [
               [
                  [-156.45, 71.26],
                  [-133, 57.51],
                  [-146.3, 61.13],
                  [-149.42, 61.51],
                  [-162.56, 54.96],
                  [-156.45, 71.26]
               ]
            ]
         ]
      },
      "properties":{
         "name":"United States"
      }
   }
]}
